open_sas/__init__.py
open_sas/cli.py
open_sas/interpreter.py
open_sas/notebook_interpreter.py
open_sas/kernel/__init__.py
open_sas/kernel/__main__.py
open_sas/kernel/install.py
open_sas/kernel/launch.py
open_sas/kernel/osas_kernel.py
open_sas/kernel/working_kernel.py
open_sas/parser/__init__.py
open_sas/parser/data_step_parser.py
open_sas/parser/macro_parser.py
open_sas/parser/proc_parser.py
open_sas/procs/__init__.py
open_sas/procs/proc_cluster.py
open_sas/procs/proc_contents.py
open_sas/procs/proc_corr.py
open_sas/procs/proc_factor.py
open_sas/procs/proc_freq.py
open_sas/procs/proc_language.py
open_sas/procs/proc_logit.py
open_sas/procs/proc_means.py
open_sas/procs/proc_ml.py
open_sas/procs/proc_npar1way.py
open_sas/procs/proc_print.py
open_sas/procs/proc_reg.py
open_sas/procs/proc_sort.py
open_sas/procs/proc_sql.py
open_sas/procs/proc_surveyselect.py
open_sas/procs/proc_timeseries.py
open_sas/procs/proc_ttest.py
open_sas/procs/proc_univariate.py
open_sas/utils/__init__.py
open_sas/utils/data_utils.py
open_sas/utils/error_handler.py
open_sas/utils/expression_evaluator.py
open_sas/utils/expression_parser.py
open_sas/utils/format_informat_parser.py
open_sas/utils/format_processor.py
open_sas/utils/libname_manager.py
open_sas/utils/macro_processor.py
open_sas/utils/sas_dataset.py
open_sas-0.1.2.dist-info/LICENSE
open_sas-0.1.2.dist-info/METADATA
open_sas-0.1.2.dist-info/WHEEL
open_sas-0.1.2.dist-info/entry_points.txt
open_sas-0.1.2.dist-info/top_level.txt
open_sas-0.1.2.dist-info/RECORD
